kimonet/__init__.py
kimonet/fileio.py
kimonet/analysis/__init__.py
kimonet/analysis/theorethical_functions.py
kimonet/analysis/trajectory_analysis.py
kimonet/analysis/trajectory_graph.py
kimonet/core/__init__.py
kimonet/core/kmc.py
kimonet/core/processes/__init__.py
kimonet/core/processes/couplings.py
kimonet/core/processes/decays.py
kimonet/core/processes/fcwd.py
kimonet/core/processes/forster.cp38-win32.pyd
kimonet/core/processes/transitions.py
kimonet/core/processes/types.py
kimonet/system/__init__.py
kimonet/system/generators.py
kimonet/system/molecule.py
kimonet/system/state.py
kimonet/system/vibrations.py
kimonet/utils/__init__.py
kimonet/utils/combinations.py
kimonet/utils/rotation.py
kimonet/utils/units.py
kimonet-0.1.4.dist-info/LICENSE
kimonet-0.1.4.dist-info/METADATA
kimonet-0.1.4.dist-info/WHEEL
kimonet-0.1.4.dist-info/top_level.txt
kimonet-0.1.4.dist-info/RECORD
