Metadata-Version: 2.1
Name: kimonet
Version: 0.1.4
Summary: kimonet module
Home-page: https://github.com/abelcarreras/kimonet
Author: Abel Carreras
Author-email: abelcarreras83@gmail.com
License: MIT License
Platform: UNKNOWN
License-File: LICENSE
Requires-Dist: numpy
Requires-Dist: scipy
Requires-Dist: matplotlib
Requires-Dist: networkx
Requires-Dist: h5py
Requires-Dist: pygraphviz
